rfoauthenticator
