Metadata-Version: 1.0
Name: rfoauthenticator
Version: 3.6
Summary: oauthenticator custom auth0 authentication
Home-page: UNKNOWN
Author: refactored
Author-email: info@refactored.ai
License: UNKNOWN
Platform: UNKNOWN
